{
  "case_id": "case-a",
  "title": "Maya R. \u2014 First headache visit",
  "mode": "first_visit",
  "description": "12-year-old with 4 months of recurrent headaches. Nonurgent migraine-compatible pattern, school impact, no red flags.",
  "patient": {
    "id": "pt-001",
    "name": "Maya R.",
    "age": 12,
    "sex": "F",
    "preferred_language": "English",
    "clinic": "Eastside Community Pediatrics",
    "mrn": "MRN 204-8817",
    "provider": "Dr. Okafor",
    "visit_length": "20 min",
    "visit_type": "First PCP headache visit",
    "chief_complaint": "New headache complaint",
    "referral_status": "New Referral - Initial Review"
  },
  "history": [
    {
      "id": "hx-1",
      "label": "Well-child visit note",
      "date": "2026-02-10",
      "text": "12-year-old female, healthy, immunizations up to date. Mother mentions occasional headaches over the winter, not evaluated. Normal growth, normal neuro screening exam. BMI 50th percentile."
    },
    {
      "id": "hx-2",
      "label": "Nurse triage call",
      "date": "2026-05-28",
      "text": "Parent called: Maya sent home from school twice this month with headache and nausea. Advised scheduling headache-focused visit."
    },
    {
      "id": "hx-3",
      "label": "Vitals (today)",
      "date": "2026-07-18",
      "text": "BP 104/66, HR 78, T 36.8C, Ht 152 cm, Wt 43 kg. No fever. Appears well."
    },
    {
      "id": "hx-4",
      "label": "Medication list & allergies",
      "date": "2026-07-18",
      "text": "No daily medications. PRN ibuprofen per parent report at check-in. PRN albuterol inhaler (mild intermittent asthma). Allergies: amoxicillin \u2014 rash (childhood)."
    },
    {
      "id": "hx-5",
      "label": "Urgent care visit note",
      "date": "2026-05-15",
      "text": "Presented with headache and nausea after school. Neuro exam grossly normal, no imaging performed. Discharged same day with ibuprofen advice; PCP follow-up recommended."
    }
  ],
  "red_flag_catalog": [
    {
      "key": "thunderclap",
      "label": "Sudden severe (thunderclap) / worst headache of life"
    },
    {
      "key": "waking_headache",
      "label": "Wakes from sleep / worst on awakening"
    },
    {
      "key": "vomiting_am",
      "label": "Early-morning vomiting unrelated to illness"
    },
    {
      "key": "exertional_valsalva",
      "label": "Triggered by cough / Valsalva / exertion"
    },
    {
      "key": "neuro_deficit",
      "label": "Focal weakness or numbness"
    },
    {
      "key": "vision_change",
      "label": "Vision changes (double vision, non-aura vision loss)"
    },
    {
      "key": "speech_difficulty",
      "label": "Difficulty speaking or understanding"
    },
    {
      "key": "gait_change",
      "label": "Imbalance or gait changes"
    },
    {
      "key": "seizures",
      "label": "Seizure history or recent seizure"
    },
    {
      "key": "altered_mental_status",
      "label": "Altered mental status / personality change"
    },
    {
      "key": "fever_stiff_neck",
      "label": "Fever, stiff neck, or systemic infection signs"
    },
    {
      "key": "cancer_immunosuppression_shunt",
      "label": "History of cancer, immune suppression, or shunt"
    },
    {
      "key": "head_trauma",
      "label": "Recent significant head trauma"
    },
    {
      "key": "worsening_pattern",
      "label": "Progressive worsening over weeks/months"
    }
  ],
  "pedmidas_questions": [
    {
      "question_id": "pm1",
      "question": "Full school days missed in last 3 months"
    },
    {
      "question_id": "pm2",
      "question": "Partial school days missed in last 3 months"
    },
    {
      "question_id": "pm3",
      "question": "School days functioning at less than half"
    },
    {
      "question_id": "pm4",
      "question": "Days unable to do home activities/chores"
    },
    {
      "question_id": "pm5",
      "question": "Days unable to join play/social/sports"
    },
    {
      "question_id": "pm6",
      "question": "Days participated in activities at less than half"
    }
  ],
  "chunks": [
    {
      "turns": [
        {
          "id": "t-1",
          "speaker": "clinician",
          "text": "So Maya, tell me about these headaches. When did they start?",
          "timestamp": "00:00:12"
        },
        {
          "id": "t-2",
          "speaker": "patient",
          "text": "Around the start of March, I guess. Like four months ago. They keep coming back.",
          "timestamp": "00:00:19"
        }
      ],
      "delta": {
        "agent_status": "Extracting headache characteristics",
        "evidence": [
          {
            "id": "ev-1",
            "source_type": "transcript",
            "source_label": "Patient, 00:00:19",
            "quote": "Around the start of March, I guess. Like four months ago. They keep coming back."
          }
        ],
        "profile": {
          "onset": {
            "value": "~4 months ago (early March 2026)",
            "status": "present",
            "evidence_ids": [
              "ev-1"
            ]
          }
        },
        "missing_questions": [
          "How many headache days per month?",
          "How long does each headache last?",
          "Where does it hurt and what does it feel like?",
          "Any nausea, vomiting, light or sound sensitivity?",
          "Any headaches that wake her from sleep?",
          "School days missed (PedMIDAS)"
        ]
      }
    },
    {
      "turns": [
        {
          "id": "t-3",
          "speaker": "clinician",
          "text": "How often are they happening now? How many days in a month would you say?",
          "timestamp": "00:01:02"
        },
        {
          "id": "t-4",
          "speaker": "parent",
          "text": "It's gotten to maybe two a week. So eight days a month, sometimes more.",
          "timestamp": "00:01:10"
        },
        {
          "id": "t-5",
          "speaker": "patient",
          "text": "They last a really long time too, like most of the afternoon until I sleep.",
          "timestamp": "00:01:21"
        },
        {
          "id": "t-5b",
          "speaker": "parent",
          "text": "It got bad enough in May that we took her to urgent care once after school. They checked her and sent us home, told us to see you.",
          "timestamp": "00:01:34"
        }
      ],
      "delta": {
        "agent_status": "Extracting headache characteristics",
        "evidence": [
          {
            "id": "ev-2",
            "source_type": "transcript",
            "source_label": "Parent, 00:01:10",
            "quote": "It's gotten to maybe two a week. So eight days a month, sometimes more."
          },
          {
            "id": "ev-3",
            "source_type": "transcript",
            "source_label": "Patient, 00:01:21",
            "quote": "They last a really long time too, like most of the afternoon until I sleep."
          },
          {
            "id": "ev-3b",
            "source_type": "transcript",
            "source_label": "Parent, 00:01:34",
            "quote": "It got bad enough in May that we took her to urgent care once after school."
          }
        ],
        "profile": {
          "frequency_days_per_month": {
            "value": 8,
            "status": "present",
            "evidence_ids": [
              "ev-2"
            ]
          },
          "episode_duration": {
            "value": "Several hours (afternoon until sleep)",
            "status": "present",
            "evidence_ids": [
              "ev-3"
            ]
          },
          "repeat_visits": {
            "value": "1 urgent-care visit for headache (May 2026); no ED visits reported",
            "status": "present",
            "evidence_ids": [
              "ev-3b"
            ]
          }
        },
        "missing_questions_remove": [
          "How many headache days per month?",
          "How long does each headache last?"
        ]
      }
    },
    {
      "turns": [
        {
          "id": "t-6",
          "speaker": "clinician",
          "text": "Where does it hurt, and what does it feel like?",
          "timestamp": "00:02:05"
        },
        {
          "id": "t-7",
          "speaker": "patient",
          "text": "Mostly here on both sides of my forehead. It's like pounding, like a drum. Pretty bad \u2014 I can't really do homework when it happens.",
          "timestamp": "00:02:14"
        },
        {
          "id": "t-7b",
          "speaker": "clinician",
          "text": "If you have one and you run around \u2014 gym class, soccer \u2014 does it get worse?",
          "timestamp": "00:02:25"
        },
        {
          "id": "t-7c",
          "speaker": "patient",
          "text": "Yeah, way worse. If I run at practice with a headache it pounds harder and I have to stop.",
          "timestamp": "00:02:31"
        },
        {
          "id": "t-2x",
          "speaker": "parent",
          "timestamp": "00:02:52",
          "text": "Maybe two of those a month are the really bad ones where she just can't do anything."
        }
      ],
      "delta": {
        "agent_status": "Extracting headache characteristics",
        "evidence": [
          {
            "id": "ev-4",
            "source_type": "transcript",
            "source_label": "Patient, 00:02:14",
            "quote": "Mostly here on both sides of my forehead. It's like pounding, like a drum. Pretty bad \u2014 I can't really do homework when it happens."
          },
          {
            "id": "ev-4b",
            "source_type": "transcript",
            "source_label": "Patient, 00:02:31",
            "quote": "Yeah, way worse. If I run at practice with a headache it pounds harder and I have to stop."
          },
          {
            "id": "ev-4x",
            "source_type": "transcript",
            "source_label": "Parent, 00:02:52",
            "quote": "Maybe two of those a month are the really bad ones where she just can't do anything."
          }
        ],
        "profile": {
          "location": {
            "value": "Bilateral frontal",
            "status": "present",
            "evidence_ids": [
              "ev-4"
            ]
          },
          "quality": {
            "value": "Pounding / throbbing",
            "status": "present",
            "evidence_ids": [
              "ev-4"
            ]
          },
          "severity": {
            "value": "Moderate\u2013severe (stops homework)",
            "status": "present",
            "evidence_ids": [
              "ev-4"
            ]
          },
          "activity_worsening": {
            "value": "Worse with routine physical activity (running at practice)",
            "status": "present",
            "evidence_ids": [
              "ev-4b"
            ]
          },
          "severe_attacks_per_month": {
            "value": 2,
            "status": "present",
            "evidence_ids": [
              "ev-4x"
            ]
          }
        },
        "missing_questions_remove": [
          "Where does it hurt and what does it feel like?"
        ]
      }
    },
    {
      "turns": [
        {
          "id": "t-8",
          "speaker": "clinician",
          "text": "When the headache comes, does she feel sick to her stomach? Bothered by light or noise?",
          "timestamp": "00:03:00"
        },
        {
          "id": "t-9",
          "speaker": "parent",
          "text": "Yes, she gets nauseous \u2014 she's thrown up once or twice. And she goes to her room and turns off the lights, says our voices are too loud.",
          "timestamp": "00:03:11"
        },
        {
          "id": "t-9b",
          "speaker": "clinician",
          "text": "Maya, right before a headache starts, do you ever see flashing lights, zigzag lines, spots \u2014 or get numbness or tingling?",
          "timestamp": "00:03:24"
        },
        {
          "id": "t-9c",
          "speaker": "patient",
          "text": "No, nothing like that. It just starts hurting.",
          "timestamp": "00:03:31"
        }
      ],
      "delta": {
        "agent_status": "Extracting headache characteristics",
        "evidence": [
          {
            "id": "ev-5",
            "source_type": "transcript",
            "source_label": "Parent, 00:03:11",
            "quote": "Yes, she gets nauseous \u2014 she's thrown up once or twice. And she goes to her room and turns off the lights, says our voices are too loud."
          },
          {
            "id": "ev-5b",
            "source_type": "transcript",
            "source_label": "Patient, 00:03:31",
            "quote": "No, nothing like that. It just starts hurting."
          }
        ],
        "profile": {
          "associated_symptoms": {
            "value": [
              "Nausea",
              "Occasional vomiting with attacks",
              "Photophobia",
              "Phonophobia"
            ],
            "status": "present",
            "evidence_ids": [
              "ev-5"
            ]
          },
          "aura": {
            "value": "No visual or sensory aura reported",
            "status": "negative",
            "evidence_ids": [
              "ev-5b"
            ]
          },
          "relievers": {
            "value": [
              "Rest in dark, quiet room"
            ],
            "status": "present",
            "evidence_ids": [
              "ev-5"
            ]
          }
        },
        "missing_questions_remove": [
          "Any nausea, vomiting, light or sound sensitivity?"
        ]
      }
    },
    {
      "turns": [
        {
          "id": "t-10",
          "speaker": "clinician",
          "text": "Important safety questions. Do headaches ever wake her up from sleep? Any vomiting first thing in the morning? Any weakness, numbness, or trouble seeing?",
          "timestamp": "00:04:02"
        },
        {
          "id": "t-11",
          "speaker": "parent",
          "text": "No, never at night \u2014 they're always afternoon or evening. No morning vomiting. Nothing like weakness or vision problems.",
          "timestamp": "00:04:18"
        },
        {
          "id": "t-12",
          "speaker": "clinician",
          "text": "Any seizures or staring spells? Changes in how she walks or her balance? Times she seemed confused or not herself? And does coughing, straining, or hard exercise ever set a headache off suddenly?",
          "timestamp": "00:04:31"
        },
        {
          "id": "t-13",
          "speaker": "parent",
          "text": "No seizures, walking is fine, she's always been sharp. Coughing or straining has never started one. And nothing sudden \u2014 they came on gradually, never a worst-headache-of-her-life moment.",
          "timestamp": "00:04:44"
        },
        {
          "id": "t-4x",
          "speaker": "clinician",
          "timestamp": "00:04:55",
          "text": "A few more: any trouble speaking or understanding during these? Fevers or a stiff neck? Any big hits to the head recently? And she's never had cancer, immune problems, or a shunt, right?"
        },
        {
          "id": "t-4y",
          "speaker": "parent",
          "timestamp": "00:05:02",
          "text": "No, speech is normal, no fevers or stiff neck, no head injuries, and none of that medical history \u2014 she's been healthy."
        }
      ],
      "delta": {
        "agent_status": "Checking red flags",
        "evidence": [
          {
            "id": "ev-6",
            "source_type": "transcript",
            "source_label": "Parent, 00:04:18",
            "quote": "No, never at night \u2014 they're always afternoon or evening. No morning vomiting. Nothing like weakness or vision problems."
          },
          {
            "id": "ev-7",
            "source_type": "transcript",
            "source_label": "Parent, 00:04:44",
            "quote": "No seizures, walking is fine, she's always been sharp. Coughing or straining has never started one. And nothing sudden \u2014 they came on gradually, never a worst-headache-of-her-life moment."
          },
          {
            "id": "ev-7b",
            "source_type": "transcript",
            "source_label": "Parent, 00:05:02",
            "quote": "No, speech is normal, no fevers or stiff neck, no head injuries, and none of that medical history \u2014 she's been healthy."
          }
        ],
        "red_flags": [
          {
            "key": "waking_headache",
            "status": "absent",
            "evidence_ids": [
              "ev-6"
            ]
          },
          {
            "key": "vomiting_am",
            "status": "absent",
            "evidence_ids": [
              "ev-6"
            ]
          },
          {
            "key": "neuro_deficit",
            "status": "absent",
            "evidence_ids": [
              "ev-6"
            ]
          },
          {
            "key": "seizures",
            "status": "absent",
            "evidence_ids": [
              "ev-7"
            ]
          },
          {
            "key": "gait_change",
            "status": "absent",
            "evidence_ids": [
              "ev-7"
            ]
          },
          {
            "key": "altered_mental_status",
            "status": "absent",
            "evidence_ids": [
              "ev-7"
            ]
          },
          {
            "key": "exertional_valsalva",
            "status": "absent",
            "evidence_ids": [
              "ev-7"
            ]
          },
          {
            "key": "thunderclap",
            "status": "absent",
            "evidence_ids": [
              "ev-7"
            ]
          },
          {
            "key": "vision_change",
            "status": "absent",
            "evidence_ids": [
              "ev-6"
            ]
          },
          {
            "key": "speech_difficulty",
            "status": "absent",
            "evidence_ids": [
              "ev-7b"
            ]
          },
          {
            "key": "fever_stiff_neck",
            "status": "absent",
            "evidence_ids": [
              "ev-7b"
            ]
          },
          {
            "key": "cancer_immunosuppression_shunt",
            "status": "absent",
            "evidence_ids": [
              "ev-7b"
            ]
          },
          {
            "key": "head_trauma",
            "status": "absent",
            "evidence_ids": [
              "ev-7b"
            ]
          }
        ],
        "missing_questions_remove": [
          "Any headaches that wake her from sleep?"
        ],
        "missing_questions_add": [
          "Is the overall pattern stable or worsening month to month?"
        ]
      }
    },
    {
      "turns": [
        {
          "id": "t-14",
          "speaker": "clinician",
          "text": "Compared to March, are they getting more frequent or stronger month over month, or about the same?",
          "timestamp": "00:05:10"
        },
        {
          "id": "t-15",
          "speaker": "parent",
          "text": "They went up in the spring but the last two months it's been about the same. Not really worse.",
          "timestamp": "00:05:20"
        }
      ],
      "delta": {
        "agent_status": "Capturing headache pattern",
        "evidence": [
          {
            "id": "ev-8",
            "source_type": "transcript",
            "source_label": "Parent, 00:05:20",
            "quote": "They went up in the spring but the last two months it's been about the same. Not really worse."
          }
        ],
        "profile": {
          "progression": {
            "value": "Rose in spring, plateaued last 2 months \u2014 non-progressive",
            "status": "present",
            "evidence_ids": [
              "ev-8"
            ]
          }
        },
        "missing_questions_remove": [
          "Is the overall pattern stable or worsening month to month?"
        ],
        "red_flags": [
          {
            "key": "worsening_pattern",
            "status": "absent",
            "evidence_ids": [
              "ev-8"
            ]
          }
        ]
      }
    },
    {
      "turns": [
        {
          "id": "t-16",
          "speaker": "clinician",
          "text": "Let's talk about school. In the last three months, how many full days has she missed because of headaches? And days she went but left early?",
          "timestamp": "00:06:05"
        },
        {
          "id": "t-17",
          "speaker": "parent",
          "text": "She missed four full days. And left early... I'd say six times.",
          "timestamp": "00:06:16"
        },
        {
          "id": "t-18",
          "speaker": "patient",
          "text": "And a lot of days I'm there but I can't focus at all, like ten days maybe I got almost nothing done.",
          "timestamp": "00:06:28"
        }
      ],
      "delta": {
        "agent_status": "Updating PedMIDAS capture",
        "evidence": [
          {
            "id": "ev-9",
            "source_type": "transcript",
            "source_label": "Parent, 00:06:16",
            "quote": "She missed four full days. And left early... I'd say six times."
          },
          {
            "id": "ev-10",
            "source_type": "transcript",
            "source_label": "Patient, 00:06:28",
            "quote": "And a lot of days I'm there but I can't focus at all, like ten days maybe I got almost nothing done."
          }
        ],
        "profile": {
          "school_impact": {
            "value": "Missed 4 full days, 6 partial days, ~10 low-function days in 3 months",
            "status": "present",
            "evidence_ids": [
              "ev-9",
              "ev-10"
            ]
          }
        },
        "pedmidas_responses": [
          {
            "question_id": "pm1",
            "value": 4,
            "evidence_ids": [
              "ev-9"
            ]
          },
          {
            "question_id": "pm2",
            "value": 6,
            "evidence_ids": [
              "ev-9"
            ]
          },
          {
            "question_id": "pm3",
            "value": 10,
            "evidence_ids": [
              "ev-10"
            ]
          }
        ],
        "missing_questions_remove": [
          "School days missed (PedMIDAS)"
        ],
        "missing_questions_add": [
          "Days unable to do chores or home activities (PedMIDAS)",
          "Days missing or limited in sports/social activities (PedMIDAS)"
        ]
      }
    },
    {
      "turns": [
        {
          "id": "t-19",
          "speaker": "clinician",
          "text": "Outside school \u2014 days she couldn't do things at home, chores, homework? And days she skipped soccer or hanging out with friends, or went but wasn't really herself?",
          "timestamp": "00:07:12"
        },
        {
          "id": "t-20",
          "speaker": "parent",
          "text": "Maybe five days she just went straight to bed and did nothing at home. She skipped soccer practice three times, and probably four more where she played but badly and came off early.",
          "timestamp": "00:07:30"
        }
      ],
      "delta": {
        "agent_status": "Updating PedMIDAS capture",
        "evidence": [
          {
            "id": "ev-11",
            "source_type": "transcript",
            "source_label": "Parent, 00:07:30",
            "quote": "Maybe five days she just went straight to bed and did nothing at home. She skipped soccer practice three times, and probably four more where she played but badly and came off early."
          }
        ],
        "profile": {
          "activity_impact": {
            "value": "Skipped soccer 3x, limited participation 4x; ~5 days no home activities in 3 months",
            "status": "present",
            "evidence_ids": [
              "ev-11"
            ]
          }
        },
        "pedmidas_responses": [
          {
            "question_id": "pm4",
            "value": 5,
            "evidence_ids": [
              "ev-11"
            ]
          },
          {
            "question_id": "pm5",
            "value": 3,
            "evidence_ids": [
              "ev-11"
            ]
          },
          {
            "question_id": "pm6",
            "value": 4,
            "evidence_ids": [
              "ev-11"
            ]
          }
        ],
        "missing_questions_remove": [
          "Days unable to do chores or home activities (PedMIDAS)",
          "Days missing or limited in sports/social activities (PedMIDAS)"
        ],
        "missing_questions_add": [
          "Sleep schedule, hydration, meals, screen time",
          "What medications is she taking for attacks and how often?"
        ]
      }
    },
    {
      "turns": [
        {
          "id": "t-21",
          "speaker": "clinician",
          "text": "Tell me about sleep, water, meals, screens.",
          "timestamp": "00:08:15"
        },
        {
          "id": "t-22",
          "speaker": "patient",
          "text": "I go to sleep around midnight, sometimes later, on my phone. I skip breakfast a lot. I don't really drink water at school.",
          "timestamp": "00:08:24"
        },
        {
          "id": "t-23",
          "speaker": "clinician",
          "text": "And what does she take when a headache hits?",
          "timestamp": "00:08:40"
        },
        {
          "id": "t-24",
          "speaker": "parent",
          "text": "Ibuprofen. Honestly, probably three times a week lately. Sometimes it helps if she takes it early.",
          "timestamp": "00:08:48"
        }
      ],
      "delta": {
        "agent_status": "Extracting habits and medication use",
        "evidence": [
          {
            "id": "ev-12",
            "source_type": "transcript",
            "source_label": "Patient, 00:08:24",
            "quote": "I go to sleep around midnight, sometimes later, on my phone. I skip breakfast a lot. I don't really drink water at school."
          },
          {
            "id": "ev-13",
            "source_type": "transcript",
            "source_label": "Parent, 00:08:48",
            "quote": "Ibuprofen. Honestly, probably three times a week lately. Sometimes it helps if she takes it early."
          },
          {
            "id": "ev-13b",
            "source_type": "history",
            "source_label": "Medication list (today)",
            "quote": "No daily medications. PRN ibuprofen per parent report at check-in."
          }
        ],
        "profile": {
          "habits": {
            "value": [
              "Late sleep (~midnight, phone in bed)",
              "Frequently skips breakfast",
              "Low water intake at school"
            ],
            "status": "present",
            "evidence_ids": [
              "ev-12"
            ]
          },
          "acute_medication_use": {
            "value": [
              "Ibuprofen ~3x/week (OTC, parent-administered)"
            ],
            "status": "needs_confirmation",
            "evidence_ids": [
              "ev-13"
            ]
          },
          "treatment_response": {
            "value": "Partial relief when ibuprofen taken early in attack; inconsistent otherwise",
            "status": "needs_confirmation",
            "evidence_ids": [
              "ev-13"
            ]
          },
          "triggers": {
            "value": [
              "Poor sleep",
              "Skipped meals",
              "Dehydration (suspected)"
            ],
            "status": "needs_confirmation",
            "evidence_ids": [
              "ev-12"
            ]
          },
          "relievers": {
            "value": [
              "Rest in dark, quiet room",
              "Ibuprofen (helps if taken early)"
            ],
            "status": "present",
            "evidence_ids": [
              "ev-5",
              "ev-13"
            ]
          },
          "medication_overuse_risk": {
            "value": "Ibuprofen ~3 days/week (~12 days/month) \u2014 meets \u226510 days/month overuse threshold",
            "status": "present",
            "evidence_ids": [
              "ev-13"
            ]
          },
          "preventive_medication_use": {
            "value": [],
            "status": "negative",
            "evidence_ids": [
              "ev-13b"
            ]
          }
        },
        "diary_days": [
          {
            "day": 2,
            "intensity": 2,
            "evidence_ids": [
              "ev-2"
            ]
          },
          {
            "day": 5,
            "intensity": 3,
            "evidence_ids": [
              "ev-2"
            ]
          },
          {
            "day": 9,
            "intensity": 2,
            "evidence_ids": [
              "ev-2"
            ]
          },
          {
            "day": 12,
            "intensity": 1,
            "evidence_ids": [
              "ev-2"
            ]
          },
          {
            "day": 16,
            "intensity": 3,
            "evidence_ids": [
              "ev-2"
            ]
          },
          {
            "day": 19,
            "intensity": 2,
            "evidence_ids": [
              "ev-2"
            ]
          },
          {
            "day": 23,
            "intensity": 2,
            "evidence_ids": [
              "ev-2"
            ]
          },
          {
            "day": 27,
            "intensity": 1,
            "evidence_ids": [
              "ev-2"
            ]
          }
        ],
        "missing_questions_remove": [
          "Sleep schedule, hydration, meals, screen time",
          "What medications is she taking for attacks and how often?"
        ],
        "missing_questions_add": [
          "Family history of migraine"
        ]
      }
    },
    {
      "turns": [
        {
          "id": "t-25",
          "speaker": "clinician",
          "text": "Does anyone in the family get migraines?",
          "timestamp": "00:09:30"
        },
        {
          "id": "t-26",
          "speaker": "parent",
          "text": "I did as a teenager, pretty bad ones. My mother too.",
          "timestamp": "00:09:36"
        },
        {
          "id": "t-9x",
          "speaker": "clinician",
          "timestamp": "00:10:05",
          "text": "Her exam today is reassuring \u2014 she's well-appearing, neuro exam is completely normal: eye movements, strength, coordination and gait all fine. I got a good look at her optic discs and there's no papilledema."
        },
        {
          "id": "t-9y",
          "speaker": "clinician",
          "timestamp": "00:10:30",
          "text": "Putting it together, this looks most like migraine \u2014 my concern level today is low. Plan: start a headache diary, work on sleep and hydration, keep ibuprofen to no more than two days a week so we don't get rebound headaches, and I'll see her back in eight weeks. No imaging needed today."
        }
      ],
      "delta": {
        "agent_status": "Preparing clinician-review plan",
        "evidence": [
          {
            "id": "ev-14",
            "source_type": "transcript",
            "source_label": "Parent, 00:09:36",
            "quote": "I did as a teenager, pretty bad ones. My mother too."
          },
          {
            "id": "ev-15",
            "source_type": "history",
            "source_label": "Vitals (today)",
            "quote": "BP 104/66, HR 78, T 36.8C. No fever. Appears well."
          },
          {
            "id": "ev-16",
            "source_type": "transcript",
            "source_label": "Clinician, 00:10:05",
            "quote": "she's well-appearing, neuro exam is completely normal: eye movements, strength, coordination and gait all fine. I got a good look at her optic discs and there's no papilledema."
          },
          {
            "id": "ev-17",
            "source_type": "transcript",
            "source_label": "Clinician, 00:10:30",
            "quote": "this looks most like migraine \u2014 my concern level today is low. Plan: start a headache diary, work on sleep and hydration, keep ibuprofen to no more than two days a week"
          }
        ],
        "missing_questions_remove": [
          "Family history of migraine"
        ],
        "missing_questions_add": [],
        "profile": {
          "family_history": {
            "value": "Mother (teenage-onset migraine) and maternal grandmother",
            "status": "present",
            "evidence_ids": [
              "ev-14"
            ]
          },
          "diary_available": {
            "value": "Not yet \u2014 starting today per plan",
            "status": "negative",
            "evidence_ids": [
              "ev-17"
            ]
          }
        },
        "exam": {
          "general_appearance": {
            "value": "Well-appearing",
            "status": "present",
            "evidence_ids": [
              "ev-16"
            ]
          },
          "neuro_exam": {
            "value": [
              "Normal \u2014 eye movements, strength, coordination, gait"
            ],
            "status": "present",
            "evidence_ids": [
              "ev-16"
            ]
          },
          "funduscopic": {
            "value": "Normal \u2014 no papilledema",
            "status": "present",
            "evidence_ids": [
              "ev-16"
            ]
          }
        },
        "clinician_assessment": {
          "impression": {
            "value": "Recurrent headaches most consistent with migraine; reassuring exam, no red flags",
            "status": "present",
            "evidence_ids": [
              "ev-17"
            ]
          },
          "concern_level": {
            "value": "Low",
            "status": "present",
            "evidence_ids": [
              "ev-17"
            ]
          },
          "tentative_classification": {
            "value": "Likely migraine",
            "status": "present",
            "evidence_ids": [
              "ev-17"
            ]
          },
          "plan_selections": {
            "value": [
              "Headache diary + follow-up (8 weeks)",
              "Lifestyle counseling (sleep, hydration)",
              "Acute treatment guidance (ibuprofen \u22642 days/week)",
              "No imaging today"
            ],
            "status": "present",
            "evidence_ids": [
              "ev-17"
            ]
          }
        }
      }
    }
  ],
  "emr_summary": {
    "headline": "Agent-assembled chart summary",
    "evidence": [
      {
        "id": "emr-ev-1",
        "source_type": "history",
        "source_label": "Medication list & allergies - 07/18",
        "quote": "No daily medications. PRN ibuprofen per parent report at check-in. PRN albuterol inhaler (mild intermittent asthma). Allergies: amoxicillin \u2014 rash (childhood)."
      },
      {
        "id": "emr-ev-2",
        "source_type": "history",
        "source_label": "Urgent care visit note - 05/15",
        "quote": "Presented with headache and nausea after school. Neuro exam grossly normal, no imaging performed. Discharged same day with ibuprofen advice; PCP follow-up recommended."
      },
      {
        "id": "emr-ev-3",
        "source_type": "history",
        "source_label": "Well-child note - 02/10",
        "quote": "Mother mentions occasional headaches over the winter, not evaluated. Normal growth, normal neuro screening exam."
      },
      {
        "id": "emr-ev-4",
        "source_type": "document",
        "source_label": "Intake form - 07/18",
        "quote": "PRN ibuprofen with minimal relief per parent report. No prior neurology contact. Mother: migraine."
      }
    ],
    "items": [
      {
        "id": "emr-1",
        "category": "pmh",
        "label": "Mild intermittent asthma",
        "detail": "Albuterol PRN, well controlled",
        "flag": "",
        "date": "",
        "evidence_ids": [
          "emr-ev-1"
        ]
      },
      {
        "id": "emr-2",
        "category": "allergy",
        "label": "Amoxicillin \u2014 rash",
        "detail": "Childhood reaction documented",
        "flag": "confirm before any prescription",
        "date": "",
        "evidence_ids": [
          "emr-ev-1"
        ]
      },
      {
        "id": "emr-3",
        "category": "family_history",
        "label": "Mother: migraine",
        "detail": "Per intake form; confirm degree/severity at visit",
        "flag": "migraine risk factor",
        "date": "2026-07-18",
        "evidence_ids": [
          "emr-ev-4"
        ]
      },
      {
        "id": "emr-4",
        "category": "medication",
        "label": "Ibuprofen PRN (parent-reported)",
        "detail": "Frequency not quantified in chart",
        "flag": "overuse watch \u2014 quantify at visit",
        "date": "2026-07-18",
        "evidence_ids": [
          "emr-ev-1",
          "emr-ev-4"
        ]
      },
      {
        "id": "emr-5",
        "category": "medication",
        "label": "Albuterol inhaler PRN",
        "detail": "For asthma",
        "flag": "no headache contraindication identified",
        "date": "",
        "evidence_ids": [
          "emr-ev-1"
        ]
      },
      {
        "id": "emr-6",
        "category": "visit_note",
        "label": "Urgent care visit \u2014 headache + nausea",
        "detail": "Normal neuro exam, no imaging, discharged same day, PCP follow-up advised",
        "flag": "repeat acute-care use for headache",
        "date": "2026-05-15",
        "evidence_ids": [
          "emr-ev-2"
        ]
      },
      {
        "id": "emr-7",
        "category": "visit_note",
        "label": "Well-child visit \u2014 headaches first mentioned",
        "detail": "Not evaluated at the time; normal neuro screen",
        "flag": "",
        "date": "2026-02-10",
        "evidence_ids": [
          "emr-ev-3"
        ]
      },
      {
        "id": "emr-8",
        "category": "imaging",
        "label": "No head imaging on file",
        "detail": "No CT/MRI ever performed",
        "flag": "baseline for escalation decision",
        "date": "",
        "evidence_ids": [
          "emr-ev-2"
        ]
      },
      {
        "id": "emr-9",
        "category": "lab",
        "label": "No headache-relevant labs",
        "detail": "Nothing in past 12 months",
        "flag": "",
        "date": "",
        "evidence_ids": []
      },
      {
        "id": "emr-10",
        "category": "referral",
        "label": "No prior neurology or ophthalmology referral",
        "detail": "First structured headache evaluation",
        "flag": "",
        "date": "",
        "evidence_ids": [
          "emr-ev-4"
        ]
      },
      {
        "id": "emr-11",
        "category": "wait_status",
        "label": "Pediatric neurology wait ~10\u201312 weeks (regional)",
        "detail": "Informs timing if escalation needed",
        "flag": "plan around wait if referring",
        "date": "2026-07-17",
        "evidence_ids": []
      },
      {
        "id": "emr-12",
        "category": "no_show",
        "label": "No missed appointments on record",
        "detail": "Family engaged with care",
        "flag": "",
        "date": "",
        "evidence_ids": []
      }
    ]
  },
  "care_plan": {
    "summary": [
      "12-year-old with ~4 months of recurrent bilateral frontal pounding headaches, ~8 days/month, lasting hours; rose in spring, non-progressive last 2 months. [ev-1, ev-2, ev-3, ev-4, ev-8]",
      "Phenotype: worse with routine activity, nausea with occasional vomiting, photophobia and phonophobia, no aura; family history of migraine (mother, grandmother). [ev-4b, ev-5, ev-5b, ev-14]",
      "Red-flag screen negative today: no thunderclap onset, morning vomiting, sleep awakening, focal deficits, seizures, gait change, altered mental status, or exertional/Valsalva trigger; normal vitals. [ev-6, ev-7, ev-15]",
      "Functional burden: PedMIDAS 32 (moderate) \u2014 4 full + 6 partial school days missed, soccer skipped/limited 7x, one urgent-care visit in May. [ev-9, ev-10, ev-11, ev-3b]",
      "Treatment response: ibuprofen ~3x/week with partial relief only when taken early \u2014 approaching overuse range; lifestyle contributors present (late sleep, skipped breakfast, low hydration). [ev-13, ev-12]"
    ],
    "questions_to_ask": [
      "Confirm exact ibuprofen dose and count per week",
      "Menstrual pattern relationship, if applicable"
    ],
    "suggested_pathway": [
      "Discuss migraine-compatible feature pattern with family (clinician review required)",
      "Start structured headache diary with family (draft provided)",
      "Lifestyle plan: regular sleep schedule, breakfast, hydration goal, screen limits at night",
      "Review acute medication strategy; counsel on limiting NSAID use to <3 days/week",
      "Consider preventive-pathway discussion if frequency/disability persists at follow-up"
    ],
    "referral_considerations": [
      "No urgent neurology referral indicated today based on negative red-flag screen (clinician to confirm)",
      "Refer if red flags emerge, pattern progresses, or disability remains moderate-high despite 8\u201312 weeks of initial plan"
    ],
    "patient_instructions": [
      "Keep the headache diary daily \u2014 one tap per day",
      "Same bedtime every night, phone out of the bedroom",
      "Eat breakfast; carry a water bottle at school",
      "Take ibuprofen early in an attack, but not more than 3 days per week",
      "Return sooner if headaches wake her at night, come with vomiting in the morning, or change suddenly"
    ],
    "disclaimer": "Draft for clinician review. Final clinical decisions remain with the clinician.",
    "evidence_ids": [
      "ev-1",
      "ev-2",
      "ev-3",
      "ev-3b",
      "ev-4",
      "ev-4b",
      "ev-5b",
      "ev-5",
      "ev-6",
      "ev-7",
      "ev-8",
      "ev-9",
      "ev-10",
      "ev-11",
      "ev-12",
      "ev-13",
      "ev-14",
      "ev-15"
    ]
  },
  "canned_qa": [
    {
      "match": [
        "school",
        "impact"
      ],
      "answer": "The family reported Maya missed 4 full school days and left early 6 times in the last 3 months, plus about 10 days where she was present but got almost nothing done. This is captured in PedMIDAS items 1\u20133.",
      "citations": [
        "ev-9",
        "ev-10"
      ]
    },
    {
      "match": [
        "red flag",
        "red-flag",
        "concerning",
        "safety"
      ],
      "answer": "All eight screened red flags are marked absent based on today's interview: no thunderclap onset, no early-morning vomiting, no headaches waking her from sleep, no focal deficits, no seizures, no gait change, no altered mental status, and no exertional/cough/Valsalva trigger. The overall pattern is also non-progressive over the last two months.",
      "citations": [
        "ev-6",
        "ev-7",
        "ev-8"
      ]
    },
    {
      "match": [
        "imaging",
        "mri",
        "ct",
        "scan"
      ],
      "answer": "The chart shows no head imaging has ever been performed \u2014 none at the May urgent-care visit (normal neuro exam, discharged same day) and none since. With today's negative red-flag screen, no imaging trigger is currently met; this remains a clinician decision.",
      "citations": [
        "emr-ev-2"
      ]
    },
    {
      "match": [
        "allerg",
        "asthma",
        "medical history",
        "pmh"
      ],
      "answer": "From the chart: mild intermittent asthma managed with PRN albuterol (no headache contraindication identified), and a documented childhood amoxicillin rash. No daily medications.",
      "citations": [
        "emr-ev-1"
      ]
    },
    {
      "match": [
        "urgent care",
        "emergency",
        "ed visit"
      ],
      "answer": "One urgent-care visit on 2026-05-15 for headache and nausea after school: normal neuro exam, no imaging, discharged the same day with PCP follow-up advised. The parent confirmed this during today's visit. No ED visits on record.",
      "citations": [
        "emr-ev-2",
        "ev-3b"
      ]
    },
    {
      "match": [
        "medication",
        "ibuprofen",
        "overuse"
      ],
      "answer": "Per parent report, Maya takes ibuprofen about 3 times per week for attacks, which approaches the medication-overuse range and is flagged for clinician review. Exact dosing was not confirmed during the visit.",
      "citations": [
        "ev-13"
      ]
    },
    {
      "match": [
        "family history",
        "family"
      ],
      "answer": "The mother reported having significant migraines as a teenager, and the maternal grandmother had them as well.",
      "citations": [
        "ev-14"
      ]
    }
  ],
  "previsit": {
    "headline": "New Referral - Initial Review",
    "documents_count": 3,
    "sources_count": 2,
    "assembled_seconds": 3.1,
    "confidence": "moderate",
    "evidence": [
      {
        "id": "pev-1",
        "source_type": "document",
        "source_label": "Intake form - 07/18",
        "quote": "Headaches about 4 months, now happening most weeks, sent home from school twice in May."
      },
      {
        "id": "pev-2",
        "source_type": "history",
        "source_label": "Nurse triage call - 05/28",
        "quote": "Maya sent home from school twice this month with headache and nausea."
      },
      {
        "id": "pev-3",
        "source_type": "history",
        "source_label": "Well-child note - 02/10",
        "quote": "Mother mentions occasional headaches over the winter, not evaluated. Normal neuro screening exam."
      },
      {
        "id": "pev-4",
        "source_type": "document",
        "source_label": "Intake form - 07/18",
        "quote": "PRN ibuprofen with minimal relief per parent report. No prior neurology contact."
      },
      {
        "id": "pev-5",
        "source_type": "document",
        "source_label": "Intake questionnaire - 07/18",
        "quote": "Red-flag screen items all answered 'no': thunderclap onset, morning vomiting, sleep awakening, focal deficits, seizures, gait change, altered mental status, exertional/Valsalva trigger."
      }
    ],
    "brief_lines": [
      {
        "id": "bl-1",
        "text": "Presenting complaint: recurrent headaches x4 months, sent home from school twice in May per triage call.",
        "source_label": "Intake form - 07/18",
        "evidence_ids": [
          "pev-1",
          "pev-2"
        ]
      },
      {
        "id": "bl-2",
        "text": "Headaches first noted at winter well-child visit; not evaluated at that time, neuro screen normal.",
        "source_label": "Well-child note - 02/10",
        "evidence_ids": [
          "pev-3"
        ]
      },
      {
        "id": "bl-3",
        "text": "No prior neurology contact, no head imaging ever performed; OTC ibuprofen tried with minimal relief.",
        "source_label": "Intake form - 07/18",
        "evidence_ids": [
          "pev-4"
        ]
      },
      {
        "id": "bl-3b",
        "text": "One urgent-care visit (05/15) for headache + nausea: normal neuro exam, discharged same day, PCP follow-up advised.",
        "source_label": "Urgent care note - 05/15",
        "evidence_ids": [
          "emr-ev-2"
        ]
      },
      {
        "id": "bl-4",
        "text": "Intake red-flag questionnaire clear - no urgent neuro red flags reported.",
        "source_label": "Intake questionnaire - 07/18",
        "evidence_ids": [
          "pev-5"
        ]
      },
      {
        "id": "bl-5",
        "text": "Baseline PedMIDAS not yet established - today's visit sets the starting point.",
        "source_label": "Visit today",
        "evidence_ids": []
      }
    ],
    "timeline": [
      {
        "date": "2026-02-10",
        "label": "Well-child visit",
        "sublabel": "Headaches mentioned, not evaluated",
        "kind": "visit"
      },
      {
        "date": "2026-05-15",
        "label": "Urgent care visit",
        "sublabel": "Headache + nausea; normal neuro exam, no imaging",
        "kind": "er_visit"
      },
      {
        "date": "2026-05-28",
        "label": "Nurse triage call",
        "sublabel": "Sent home from school twice; visit advised",
        "kind": "call"
      },
      {
        "date": "2026-07-17",
        "label": "Records assembled",
        "sublabel": "Intake form + prior notes pulled by Bridge",
        "kind": "records"
      },
      {
        "date": "2026-07-18",
        "label": "Today",
        "sublabel": "First PCP headache visit",
        "kind": "today"
      }
    ],
    "referral_snapshot": {
      "reason": "Headaches x4 months, worsening frequency",
      "duration": "Since March 2026",
      "prior_workup": "None - first structured evaluation",
      "family_history": "Mother: migraine (per intake form)"
    },
    "prior_evaluations": [
      {
        "id": "pe-1",
        "title": "Well-child visit - Feb 10",
        "detail": "Occasional headaches noted, normal neuro screen, no workup",
        "evidence_ids": [
          "pev-3"
        ]
      },
      {
        "id": "pe-2",
        "title": "OTC ibuprofen trialed at home",
        "detail": "Parent reports minimal relief, inconsistent dosing",
        "evidence_ids": [
          "pev-4"
        ]
      },
      {
        "id": "pe-3",
        "title": "No prior specialist contact",
        "detail": "This is the first structured evaluation",
        "evidence_ids": [
          "pev-4"
        ]
      }
    ],
    "family_developmental_history": [
      "Mother with migraine history (per intake form)",
      "Development on track; doing well in school until recent absences"
    ],
    "draft_plan": [
      {
        "id": "dp-1",
        "title": "Complete structured headache history",
        "detail": "Frequency, triggers, aura features - this visit",
        "evidence_ids": []
      },
      {
        "id": "dp-2",
        "title": "Start headache diary + acute treatment review",
        "detail": "Confirm ibuprofen dose/frequency; watch overuse range",
        "evidence_ids": [
          "pev-4"
        ]
      },
      {
        "id": "dp-3",
        "title": "Administer PedMIDAS today",
        "detail": "Establishes baseline for future trend tracking",
        "evidence_ids": []
      },
      {
        "id": "dp-4",
        "title": "Referral threshold",
        "detail": "Refer to neurology if red flags emerge or frequency worsens despite treatment",
        "evidence_ids": []
      }
    ],
    "ask_during_visit": [
      "How often are headaches occurring - any pattern?",
      "Any vision changes, vomiting, or morning headaches?",
      "Barriers to consistent acute treatment?"
    ],
    "handoff_items": [
      {
        "id": "ho-1",
        "title": "Family headache diary card",
        "detail": "Track frequency & triggers before next visit",
        "status": "draft_ready"
      },
      {
        "id": "ho-2",
        "title": "Neurology referral - pending decision",
        "detail": "Hold unless red flags or poor response",
        "status": "not_sent"
      }
    ],
    "unresolved_items": [
      {
        "id": "ur-1",
        "text": "Triage call mentions school nurse log - not yet received in records.",
        "requested_from": "School health office",
        "date": "2026-07-17"
      }
    ],
    "suggested_questions": [
      "Ask about this chart...",
      "Any red flags on intake screen?",
      "What happened at the well-child visit?"
    ]
  }
}